main.py
calculator_mcp_server-0.1.1.dist-info/METADATA
calculator_mcp_server-0.1.1.dist-info/WHEEL
calculator_mcp_server-0.1.1.dist-info/entry_points.txt
calculator_mcp_server-0.1.1.dist-info/top_level.txt
calculator_mcp_server-0.1.1.dist-info/RECORD
